homepanelapi
