Metadata-Version: 2.1
Name: homepanelapi
Version: 1.0.5
Summary: UNKNOWN
Home-page: https://github.com/timmo001/python-homepanelapi
Author: Timmo
Author-email: contact@timmo.xyz
License: UNKNOWN
Platform: UNKNOWN
Classifier: Programming Language :: Python :: 3
Classifier: License :: OSI Approved :: MIT License
Classifier: Operating System :: OS Independent
